cloudflare_stream_downloader/__init__.py
cloudflare_stream_downloader/main.py
cloudflare_stream_downloader-0.1.1.dist-info/licenses/LICENSE
cloudflare_stream_downloader-0.1.1.dist-info/METADATA
cloudflare_stream_downloader-0.1.1.dist-info/WHEEL
cloudflare_stream_downloader-0.1.1.dist-info/entry_points.txt
cloudflare_stream_downloader-0.1.1.dist-info/top_level.txt
cloudflare_stream_downloader-0.1.1.dist-info/RECORD
