Metadata-Version: 2.4
Name: cloudflare-stream-downloader
Version: 0.1.1
Summary: A Python tool to download Cloudflare Stream videos with automatic FFmpeg management.
Author-email: LovelyO0Sam <lovelysam2333@outlook.com>
Project-URL: Homepage, https://github.com/LovelyO0Sam/cloudflare-stream-downloader
Project-URL: Bug Tracker, https://github.com/LovelyO0Sam/cloudflare-stream-downloader/issues
Classifier: Programming Language :: Python :: 3
Classifier: License :: OSI Approved :: MIT License
Classifier: Operating System :: OS Independent
Classifier: Topic :: Multimedia :: Video
Classifier: Topic :: Utilities
Requires-Python: >=3.8
License-File: LICENSE
Requires-Dist: requests
Dynamic: license-file
